serializer/__init__.py
serializer/interface.py
python_serializer-1.0.2.dist-info/LICENSE
python_serializer-1.0.2.dist-info/METADATA
python_serializer-1.0.2.dist-info/WHEEL
python_serializer-1.0.2.dist-info/top_level.txt
python_serializer-1.0.2.dist-info/RECORD
