Metadata-Version: 2.1
Name: python-serializer
Version: 1.0.2
Summary: A Python Object-JSON-Object serializer package
Home-page: https://github.com/ximihoque/python-serializer
Author: Ximi Hoque
Author-email: hoque.ximi@gmail.com
License: UNKNOWN
Platform: UNKNOWN
Classifier: Programming Language :: Python :: 3
Classifier: License :: OSI Approved :: MIT License
Classifier: Operating System :: OS Independent
Requires-Python: >=3.6
